pyaoi.py
pyaoi-2.5.0.dist-info/LICENSE.md
pyaoi-2.5.0.dist-info/METADATA
pyaoi-2.5.0.dist-info/WHEEL
pyaoi-2.5.0.dist-info/top_level.txt
pyaoi-2.5.0.dist-info/RECORD
