Metadata-Version: 2.1
Name: pyaoi
Version: 2.5.0
Summary: A collection of useful functions operating on iterables
Home-page: https://github.com/JonasMuehlmann/pyaoi
Author: Jonas Muehlmann
Author-email: jonasmuehlmann@protonmail.com
License: UNKNOWN
Platform: UNKNOWN
Classifier: Programming Language :: Python :: 3
Classifier: License :: OSI Approved :: MIT License
Classifier: Operating System :: OS Independent
Classifier: Intended Audience :: Developers
Classifier: Topic :: Utilities
Classifier: Topic :: Software Development :: Libraries
Classifier: Topic :: Software Development :: Libraries :: Python Modules
Requires-Python: >=3.6
